<Row ss:AutoFitHeight="0" ss:Height="27">
    <Cell ss:MergeDown="1" ss:StyleID="m356909336" ><Data ss:Type="Number" th:text="${cell0}"></Data></Cell>
    <Cell ss:MergeDown="1" ss:StyleID="m356909356"><Data ss:Type="String"  th:text="${cell1}"></Data></Cell>
    <Cell ss:MergeDown="1" ss:StyleID="m356909376"><Data ss:Type="String"  th:text="${cell2}"></Data></Cell>
    <Cell ss:MergeDown="1" ss:StyleID="m356909396"><Data ss:Type="String"  th:text="${cell3}"></Data></Cell>
    <Cell ss:MergeDown="1" ss:StyleID="m356909416"><Data ss:Type="String"  ></Data></Cell>
    <Cell ss:StyleID="s78"><Data ss:Type="Number">计划</Data></Cell>
    <Cell ss:StyleID="s91"><Data ss:Type="Number" th:text="${cell4}"></Data></Cell>
    <Cell ss:StyleID="s91"><Data ss:Type="Number" th:text="${cell5}"></Data></Cell>
    <Cell ss:StyleID="s91"><Data ss:Type="Number" th:text="${cell6}"></Data></Cell>
    <Cell ss:StyleID="s91"><Data ss:Type="Number" th:text="${cell7}"></Data></Cell>
    <Cell ss:StyleID="s91"><Data ss:Type="Number" th:text="${cell8}"></Data></Cell>
    <Cell ss:StyleID="s91"><Data ss:Type="Number" th:text="${cell9}"></Data></Cell>
    <Cell ss:StyleID="s91"><Data ss:Type="Number" th:text="${cell10}"></Data></Cell>
    <Cell ss:StyleID="s91"><Data ss:Type="Number" th:text="${cell11}"></Data></Cell>
    <Cell ss:StyleID="s91"><Data ss:Type="Number" th:text="${cell12}"></Data></Cell>
    <Cell ss:StyleID="s91"><Data ss:Type="Number" th:text="${cell13}"></Data></Cell>
    <Cell ss:StyleID="s91"><Data ss:Type="Number" th:text="${cell14}"></Data></Cell>
    <Cell ss:StyleID="s91"><Data ss:Type="Number" th:text="${cell15}"></Data></Cell>
    <Cell ss:StyleID="s91"><Data ss:Type="Number" th:text="${cell16}"></Data></Cell>
    <Cell ss:StyleID="s91"><Data ss:Type="Number" th:text="${cell17}"></Data></Cell>
    <Cell ss:StyleID="s91"><Data ss:Type="Number" th:text="${cell18}"></Data></Cell>
    <Cell ss:StyleID="s91"><Data ss:Type="Number" th:text="${cell19}"></Data></Cell>
    <Cell ss:StyleID="s91"><Data ss:Type="Number" th:text="${cell20}"></Data></Cell>
    <Cell ss:StyleID="s91"><Data ss:Type="Number" th:text="${cell21}"></Data></Cell>
    <Cell ss:StyleID="s91"><Data ss:Type="Number" th:text="${cell22}"></Data></Cell>
    <Cell ss:StyleID="s91"><Data ss:Type="Number" th:text="${cell23}"></Data></Cell>
    <Cell ss:StyleID="s91"><Data ss:Type="Number" th:text="${cell24}"></Data></Cell>
    <Cell ss:StyleID="s91"><Data ss:Type="Number" th:text="${cell25}"></Data></Cell>
    <Cell ss:StyleID="s91"><Data ss:Type="Number" th:text="${cell26}"></Data></Cell>
    <Cell ss:StyleID="s91"><Data ss:Type="Number" th:text="${cell27}"></Data></Cell>
    <Cell ss:StyleID="s91"><Data ss:Type="Number" th:text="${cell28}"></Data></Cell>
    <Cell ss:StyleID="s91"><Data ss:Type="Number" th:text="${cell29}"></Data></Cell>
    <Cell ss:StyleID="s91"><Data ss:Type="Number" th:text="${cell30}"></Data></Cell>
    <Cell ss:StyleID="s91"><Data ss:Type="Number" th:text="${cell31}"></Data></Cell>
    <Cell ss:StyleID="s91"><Data ss:Type="Number" th:text="${cell32}"></Data></Cell>
    <Cell ss:StyleID="s91"><Data ss:Type="Number" th:text="${cell33}"></Data></Cell>
    <Cell ss:StyleID="s91"><Data ss:Type="Number" th:text="${cell34}"></Data></Cell>
    <Cell ss:StyleID="s91"><Data ss:Type="Number" th:text="${cell35}"></Data></Cell>
    <Cell ss:StyleID="s91"><Data ss:Type="Number" th:text="${cell36}"></Data></Cell>
    <Cell ss:StyleID="s91"><Data ss:Type="Number" th:text="${cell37}"></Data></Cell>
    <Cell ss:StyleID="s78"><Data ss:Type="Number" th:text="${cell38}"></Data></Cell>
   </Row>